app/__init__.py
app/templates/module_one/hello.html
Template_pip_package_test-0.1.1.dist-info/LICENSE.txt
Template_pip_package_test-0.1.1.dist-info/METADATA
Template_pip_package_test-0.1.1.dist-info/WHEEL
Template_pip_package_test-0.1.1.dist-info/top_level.txt
Template_pip_package_test-0.1.1.dist-info/RECORD
